{
    "project_name": "micro-django42-demo",
    "project_slug": "{{ cookiecutter.project_name.replace(' ', '_').replace('-', '_').lower().strip('-') }}",
    "project_noslug": "{{ cookiecutter.project_name.replace(' ', '').replace('-', '').lower().strip('') }}",
    "repo_private_or_public": "public",
    "domain_name": "example.com",
    "docker_service_web": "web_django",
    "debug": "y",
    "timezone": "UTC",
    "owner_login": "simkimsia",
    "some_other_variable": "some_other_value",
    "_copy_without_render": ["*config.yml"]
  }
